{
    "backend": "django",
    "db_name": "",
    "db_pass": "",
    "db_type": "mysql",
    "db_user": "",
    "dbms": "1",
    "description": "generated product",
    "design": "datta-able",
    "docker": "0",
    "err_code": 0,
    "frontend": "",
    "github_repo": "https://github.com/appseed-projects/98ea6d9b-02e8-4d0e-a1fd-f241845a950c",
    "heroku": "0",
    "pattern": "mvc",
    "pro": "0",
    "task_id": "98ea6d9b-02e8-4d0e-a1fd-f241845a950c",
    "task_info": "Upload Sources [0%] - 162 files",
    "task_output": "98ea6d9b-02e8-4d0e-a1fd-f241845a950c.zip",
    "task_result": "SUCCESS",
    "task_state": "RUNNING",
    "task_ts_end": "2022-06-29-07-42-53",
    "task_ts_start": "2022-06-29-07-42-50"
}